[
{ "text": "전자제품", "hint": "전기로 작동하는 물건" },
{ "text": "난간", "hint": "계단이나 다리 옆의 손잡이" },
{ "text": "손목시계", "hint": "손목에 차는 시계" },
{ "text": "텔레비전", "hint": "TV, 방송을 보는 기계" },
{ "text": "택배", "hint": "물건을 집까지 배달해주는 것" },
{ "text": "알람", "hint": "정해진 시간에 울리는 소리" },
{ "text": "이부자리", "hint": "이불과 요를 합쳐 부르는 말" },
{ "text": "잠옷", "hint": "잠잘 때 입는 옷" },
{ "text": "고리", "hint": "둥글게 만든 물건을 거는 것" },
{ "text": "수달피", "hint": "수달의 가죽" },
{ "text": "페인트", "hint": "색을 칠하는 물감" },
{ "text": "연", "hint": "바람에 날리는 놀이 기구" },
{ "text": "동아줄", "hint": "굵게 꼰 밧줄" },
{ "text": "모서리", "hint": "물건의 뾰족한 귀퉁이" },
{ "text": "세제", "hint": "빨래나 설거지할 때 쓰는 비누" },
{ "text": "은구슬", "hint": "은색 구슬" },
{ "text": "금구슬", "hint": "금색 구슬" },
{ "text": "먼지", "hint": "공기 중에 떠다니는 작은 티끌​​​​​​​​​​​​​​​​" }
]
