[
  { "text": "태극기", "hint": "우리나라 국기" },
  { "text": "태극", "hint": "음과 양의 조화" },
  { "text": "평화", "hint": "전쟁이 없이 평온한 것" },
  { "text": "국경일", "hint": "나라의 기념일" },
  { "text": "기념일", "hint": "기억하는 날" },
  { "text": "현충일", "hint": "나라 위해 돌아가신 분 기리는 날" },
  { "text": "깃봉", "hint": "깃대 맨 위의 둥근 것" },
  { "text": "건곤감리", "hint": "태극기 네 귀퉁이 무늬" },
  { "text": "한글", "hint": "우리나라 글자" },
  { "text": "세종 대왕", "hint": "한글을 만드신 임금님" },
  { "text": "한복", "hint": "우리나라 전통 옷" },
  { "text": "추석", "hint": "가을 명절, 송편 먹어요" },
  { "text": "설날", "hint": "새해 첫날, 떡국 먹어요" },
  { "text": "정월대보름", "hint": "음력 1월 15일 명절" },
  { "text": "아리랑", "hint": "우리나라 전통 노래" },
  { "text": "탈춤", "hint": "탈을 쓰고 추는 춤" },
  { "text": "오방색", "hint": "다섯 가지 색깔" },
  { "text": "한옥", "hint": "우리나라 전통 집" },
  { "text": "북한", "hint": "한반도 북쪽 나라" },
  { "text": "통일", "hint": "남북이 하나 되는 것" },
  { "text": "꽃술", "hint": "무궁화 가운데에 있어요" }
 ]
